settrade_v2/__init__.py
settrade_v2/_version.py
settrade_v2/config.py
settrade_v2/context.py
settrade_v2/derivatives.py
settrade_v2/equity.py
settrade_v2/errors.py
settrade_v2/logger.py
settrade_v2/market.py
settrade_v2/realtime.py
settrade_v2/user.py
settrade_v2/util.py
settrade_v2/pb/__init__.py
settrade_v2/pb/bidofferv3_pb2.py
settrade_v2/pb/candlestickv3_pb2.py
settrade_v2/pb/exchinfodvv3_pb2.py
settrade_v2/pb/exchinfoeqv3_pb2.py
settrade_v2/pb/infov3_pb2.py
settrade_v2/pb/orderdvv3_pb2.py
settrade_v2/pb/ordereqv3_pb2.py
settrade_v2/pb/google/__init__.py
settrade_v2/pb/google/type.py
settrade_v2-2.2.1.dist-info/METADATA
settrade_v2-2.2.1.dist-info/WHEEL
settrade_v2-2.2.1.dist-info/top_level.txt
settrade_v2-2.2.1.dist-info/RECORD
